INSTALL.rst
LICENSE
MANIFEST.in
README.rst
setup.cfg
setup.py
doc/Makefile
doc/conf.py
doc/example.rst
doc/index.rst
doc/make.bat
sphinxcontrib/__init__.py
sphinxcontrib/bayesnet.py
sphinxcontrib_bayesnet.egg-info/PKG-INFO
sphinxcontrib_bayesnet.egg-info/SOURCES.txt
sphinxcontrib_bayesnet.egg-info/dependency_links.txt
sphinxcontrib_bayesnet.egg-info/namespace_packages.txt
sphinxcontrib_bayesnet.egg-info/not-zip-safe
sphinxcontrib_bayesnet.egg-info/requires.txt
sphinxcontrib_bayesnet.egg-info/top_level.txt