Metadata-Version: 1.1
Name: sphinxcontrib-bayesnet
Version: 0.3
Summary: BayesNet extension for Sphinx
Home-page: https://github.com/jluttine/sphinx-bayesnet
Author: Jaakko Luttinen
Author-email: jaakko.luttinen@iki.fi
License: UNKNOWN
Download-URL: http://pypi.python.org/pypi/sphinxcontrib-bayesnet
Platform: any
Classifier: Development Status :: 4 - Beta
Classifier: Environment :: Console
Classifier: Environment :: Web Environment
Classifier: Intended Audience :: Developers
Classifier: License :: OSI Approved :: GNU General Public License v3 (GPLv3)
Classifier: Operating System :: OS Independent
Classifier: Programming Language :: Python
Classifier: Topic :: Documentation
Classifier: Topic :: Utilities
